odoo/addons/crm_claim/README.rst
odoo/addons/crm_claim/__init__.py
odoo/addons/crm_claim/__manifest__.py
odoo/addons/crm_claim/data/crm_claim_data.xml
odoo/addons/crm_claim/demo/crm_claim_demo.xml
odoo/addons/crm_claim/i18n/ca.po
odoo/addons/crm_claim/i18n/crm_claim.pot
odoo/addons/crm_claim/i18n/de.po
odoo/addons/crm_claim/i18n/es.po
odoo/addons/crm_claim/i18n/es_CO.po
odoo/addons/crm_claim/i18n/fr.po
odoo/addons/crm_claim/i18n/fr_FR.po
odoo/addons/crm_claim/i18n/gl.po
odoo/addons/crm_claim/i18n/hr.po
odoo/addons/crm_claim/i18n/it.po
odoo/addons/crm_claim/i18n/pt_BR.po
odoo/addons/crm_claim/models/__init__.py
odoo/addons/crm_claim/models/crm_claim.py
odoo/addons/crm_claim/models/crm_claim_category.py
odoo/addons/crm_claim/models/crm_claim_stage.py
odoo/addons/crm_claim/models/res_partner.py
odoo/addons/crm_claim/readme/CONFIGURE.md
odoo/addons/crm_claim/readme/CONTRIBUTORS.md
odoo/addons/crm_claim/readme/DESCRIPTION.md
odoo/addons/crm_claim/readme/HISTORY.md
odoo/addons/crm_claim/readme/USAGE.md
odoo/addons/crm_claim/report/__init__.py
odoo/addons/crm_claim/report/crm_claim_report.py
odoo/addons/crm_claim/report/crm_claim_report_view.xml
odoo/addons/crm_claim/security/crm_claim_security.xml
odoo/addons/crm_claim/security/ir.model.access.csv
odoo/addons/crm_claim/static/description/icon.png
odoo/addons/crm_claim/static/description/index.html
odoo/addons/crm_claim/tests/__init__.py
odoo/addons/crm_claim/tests/test_crm_claim.py
odoo/addons/crm_claim/views/crm_claim_category_views.xml
odoo/addons/crm_claim/views/crm_claim_menu.xml
odoo/addons/crm_claim/views/crm_claim_stage_views.xml
odoo/addons/crm_claim/views/crm_claim_views.xml
odoo/addons/crm_claim/views/res_partner_views.xml
odoo_addon_crm_claim-18.0.1.0.0.7.dist-info/METADATA
odoo_addon_crm_claim-18.0.1.0.0.7.dist-info/WHEEL
odoo_addon_crm_claim-18.0.1.0.0.7.dist-info/top_level.txt
odoo_addon_crm_claim-18.0.1.0.0.7.dist-info/RECORD
